e_commerce_packing/__init__.py
e_commerce_packing/get_workflow.py
e_commerce_packing/main.py
e_commerce_packing-0.1.14.dist-info/METADATA
e_commerce_packing-0.1.14.dist-info/WHEEL
e_commerce_packing-0.1.14.dist-info/entry_points.txt
e_commerce_packing-0.1.14.dist-info/top_level.txt
e_commerce_packing-0.1.14.dist-info/RECORD
